ccn_nx/__init__.py
ccn_nx-0.0.3.dist-info/licenses/LICENSE
ccn_nx-0.0.3.dist-info/METADATA
ccn_nx-0.0.3.dist-info/WHEEL
ccn_nx-0.0.3.dist-info/top_level.txt
ccn_nx-0.0.3.dist-info/RECORD
